houseregression_model/VERSION
houseregression_model/__init__.py
houseregression_model/config.yml
houseregression_model/pipeline.py
houseregression_model/predict.py
houseregression_model/train_pipeline.py
houseregression_model/config/__init__.py
houseregression_model/config/core.py
houseregression_model/datasets/test.csv
houseregression_model/datasets/train.csv
houseregression_model/processing/__init__.py
houseregression_model/processing/features.py
houseregression_model/processing/utility_functions.py
houseregression_model/processing/validation.py
houseregression_model/trained_models/regression_model_output_v0.2.1.pkl
tid_houseregression_model-0.2.1.dist-info/LICENCE
tid_houseregression_model-0.2.1.dist-info/METADATA
tid_houseregression_model-0.2.1.dist-info/WHEEL
tid_houseregression_model-0.2.1.dist-info/top_level.txt
tid_houseregression_model-0.2.1.dist-info/RECORD
